<?xml version="1.0" encoding="UTF-8"?>
<jcr:root xmlns:sling="http://sling.apache.org/jcr/sling/1.0" xmlns:cq="http://www.day.com/jcr/cq/1.0" xmlns:jcr="http://www.jcp.org/jcr/1.0" xmlns:nt="http://www.jcp.org/jcr/nt/1.0" xmlns:rep="internal"
    jcr:mixinTypes="[rep:AccessControllable]"
    jcr:primaryType="cq:Page">
    <rep:policy/>
    <wcm jcr:primaryType="nt:unstructured">
        <foundation jcr:primaryType="nt:unstructured">
            <components jcr:primaryType="nt:unstructured">
                <responsivegrid jcr:primaryType="nt:unstructured">
                    <content-default
                        jcr:description="Policy for editable layout containers"
                        jcr:lastModified="{Date}2019-07-13T16:34:11.734+07:00"
                        jcr:lastModifiedBy="admin"
                        jcr:primaryType="nt:unstructured"
                        jcr:title="SanDiego Site Default"
                        sling:resourceType="wcm/core/components/policy/policy"
                        components="[/libs/wcm/foundation/components/responsivegrid,group:SEA.Content,/apps/sandiego/components/form/container]"
                        policyResourceType="wcm/foundation/components/responsivegrid">
                        <cq:authoring jcr:primaryType="nt:unstructured">
                            <assetToComponentMapping jcr:primaryType="nt:unstructured"/>
                        </cq:authoring>
                        <jcr:content
                            jcr:primaryType="nt:unstructured"
                            mergeList="{Boolean}true"/>
                    </content-default>
                    <policy_109738412366600
                        jcr:lastModified="{Date}2019-07-13T16:44:05.594+07:00"
                        jcr:lastModifiedBy="admin"
                        jcr:primaryType="nt:unstructured"
                        jcr:title="Public Page Pocily"
                        sling:resourceType="wcm/core/components/policy/policy"
                        components="[/libs/wcm/foundation/components/responsivegrid,/apps/sandiego/components/content/core/carousel,/apps/sandiego/components/content/core/image,/apps/sandiego/components/content/core/navigation,/apps/sandiego/components/content/core/search,/apps/sandiego/components/content/core/tabs,/apps/sandiego/components/content/core/teaser,/apps/sandiego/components/content/core/text,/apps/sandiego/components/content/core/title,group:SEA.Content Form]">
                        <jcr:content jcr:primaryType="nt:unstructured"/>
                        <cq:styleGroups jcr:primaryType="nt:unstructured">
                            <item0 jcr:primaryType="nt:unstructured">
                                <cq:styles jcr:primaryType="nt:unstructured">
                                    <item0
                                        cq:styleClasses="cmp-layout-container--fixed"
                                        cq:styleId="1563011012274"
                                        cq:styleLabel="Fixed Container"
                                        jcr:primaryType="nt:unstructured"/>
                                </cq:styles>
                            </item0>
                        </cq:styleGroups>
                    </policy_109738412366600>
                </responsivegrid>
            </components>
        </foundation>
    </wcm>
    <sandiego jcr:primaryType="nt:unstructured">
        <components jcr:primaryType="nt:unstructured">
            <form jcr:primaryType="nt:unstructured">
                <container jcr:primaryType="nt:unstructured">
                    <form-container
                        jcr:primaryType="nt:unstructured"
                        jcr:title="SanDiego Site Form"
                        sling:resourceType="wcm/core/components/policy/policy"
                        components="[/apps/sandiego/components/form/button,/apps/sandiego/components/form/hidden,/apps/sandiego/components/form/options,/apps/sandiego/components/form/text]">
                        <jcr:content jcr:primaryType="nt:unstructured"/>
                    </form-container>
                </container>
            </form>
        </components>
    </sandiego>
</jcr:root>
